llama_cpp_openai/__init__.py
llama_cpp_openai/_api_server.py
llama_cpp_openai/_llama_2_functionary_chat_handler.py
llama_cpp_openai-0.1.1.dist-info/LICENSE
llama_cpp_openai-0.1.1.dist-info/METADATA
llama_cpp_openai-0.1.1.dist-info/WHEEL
llama_cpp_openai-0.1.1.dist-info/entry_points.txt
llama_cpp_openai-0.1.1.dist-info/RECORD
