Metadata-Version: 2.1
Name: llama_cpp_openai
Version: 0.1.1
Summary: Lightweight OpenAI API server on top of Llama local models. Suitable for combined use with Microsoft AutoGen.
License: Apache-2.0
Author: blav
Author-email: blav@actar.us
Requires-Python: >=3.8,<3.12
Classifier: Intended Audience :: Developers
Classifier: License :: OSI Approved :: Apache Software License
Classifier: Operating System :: MacOS
Classifier: Operating System :: Microsoft :: Windows
Classifier: Operating System :: OS Independent
Classifier: Operating System :: POSIX
Classifier: Operating System :: POSIX :: Linux
Classifier: Programming Language :: Python :: 3
Classifier: Programming Language :: Python :: 3.8
Classifier: Programming Language :: Python :: 3.9
Classifier: Programming Language :: Python :: 3.10
Classifier: Programming Language :: Python :: 3.11
Classifier: Topic :: Software Development :: Libraries :: Python Modules
Requires-Dist: fastapi (>=0.105.0,<0.106.0)
Requires-Dist: llama-cpp-python (>=0.2.22,<0.3.0)
Requires-Dist: pydantic (>=2.5.2,<3.0.0)
Requires-Dist: uvicorn (>=0.24.0.post1,<0.25.0)
